imageio_ffmpeg/__init__.py
imageio_ffmpeg/_definitions.py
imageio_ffmpeg/_io.py
imageio_ffmpeg/_parsing.py
imageio_ffmpeg/_utils.py
imageio_ffmpeg/binaries/README.md
imageio_ffmpeg/binaries/ffmpeg-linuxaarch64-v4.2.2
imageio_ffmpeg-0.5.0.dist-info/LICENSE
imageio_ffmpeg-0.5.0.dist-info/METADATA
imageio_ffmpeg-0.5.0.dist-info/WHEEL
imageio_ffmpeg-0.5.0.dist-info/top_level.txt
imageio_ffmpeg-0.5.0.dist-info/RECORD
