Metadata-Version: 2.1
Name: imageio-ffmpeg
Version: 0.5.0
Summary: FFMPEG wrapper for Python
Home-page: https://github.com/imageio/imageio-ffmpeg
Download-URL: http://pypi.python.org/pypi/imageio-ffmpeg
Author: imageio contributors
Author-email: almar.klein@gmail.com
License: BSD-2-Clause
Keywords: video ffmpeg
Platform: any
Classifier: Development Status :: 5 - Production/Stable
Classifier: Intended Audience :: Science/Research
Classifier: Intended Audience :: Education
Classifier: Intended Audience :: Developers
Classifier: License :: OSI Approved :: BSD License
Classifier: Operating System :: MacOS :: MacOS X
Classifier: Operating System :: Microsoft :: Windows
Classifier: Operating System :: POSIX
Classifier: Programming Language :: Python
Classifier: Programming Language :: Python :: 3
Classifier: Programming Language :: Python :: 3.7
Classifier: Programming Language :: Python :: 3.8
Classifier: Programming Language :: Python :: 3.9
Classifier: Programming Language :: Python :: 3.10
Classifier: Programming Language :: Python :: 3.11
Classifier: Programming Language :: Python :: 3.12
Provides: imageio_ffmpeg
Requires-Python: >=3.5
License-File: LICENSE
